[1,0,0,[["cc.JsonAsset",["_name","json"],1]],[[0,0,1,3]],[[0,"Level1B",[{"ID":1,"wave":1,"hp":20,"atk":2,"EnemyId":1,"EnemyNum":5,"time":0,"Space":0.7,"PositionX":[100,620]},{"ID":2,"wave":2,"hp":20,"atk":2,"EnemyId":1,"EnemyNum":6,"time":0,"Space":0.7,"PositionX":[100,620]},{"ID":3,"wave":3,"hp":20,"atk":2,"EnemyId":1,"EnemyNum":7,"time":0,"Space":0.7,"PositionX":[100,620]},{"ID":4,"wave":4,"hp":40,"atk":2,"EnemyId":1,"EnemyNum":7,"time":1,"Space":0.7,"PositionX":[100,620]},{"ID":5,"wave":4,"hp":30,"atk":4,"EnemyId":9,"EnemyNum":2,"time":5.9,"Space":0.7,"PositionX":[100,620]},{"ID":6,"wave":5,"hp":60,"atk":2,"EnemyId":1,"EnemyNum":8,"time":1,"Space":0.7,"PositionX":[100,620]},{"ID":7,"wave":5,"hp":40,"atk":4,"EnemyId":9,"EnemyNum":3,"time":6.6,"Space":0.7,"PositionX":[100,620]},{"ID":8,"wave":5,"hp":700,"atk":8,"EnemyId":101,"EnemyNum":1,"time":8.7,"Space":0.7,"PositionX":[100,620]}]]],0,0,[],[],[]]