[1,["ecpdLyjvZBwrvm+cedCcQy","90jDIXFPFPcZfsDyzRKwMO","25xIKu+G9PBq3GEvx2y6Ao","beEFTB6UVCz4PcngDi38zE","ebFfaUFt5PFrSeeE+kO1q1"],["node","_spriteFrame","_N$file","root","target","data","_textureSetter"],[["cc.Node",["_name","_components","_prefab","_contentSize","_trs","_parent","_children","_anchorPoint"],2,9,4,5,7,1,2,5],["cc.PrefabInfo",["fileId","root"],2,1],["cc.LabelOutline",["_width","_enabled","node","_color"],1,1,5],["cc.Sprite",["node","_materials","_spriteFrame"],3,1,3,6],"cc.SpriteFrame",["cc.Prefab",["_name"],2],["d0c4d+PsndNm4cOO+dpx32j",["node"],3,1],["cc.Button",["node","clickEvents"],3,1,9],["cc.ClickEvent",["_componentId","handler","target"],1,1],["cc.Label",["_string","_fontSize","_lineHeight","_isSystemFontUsed","_N$horizontalAlign","_N$verticalAlign","node","_materials","_N$file"],-3,1,3,6]],[[1,0,1,2],[0,0,5,1,2,3,4,2],[9,0,1,2,3,4,5,6,7,8,7],[3,0,1,2,1],[5,0,2],[0,0,6,1,2,3,4,2],[0,0,5,1,2,3,7,4,2],[6,0,1],[7,0,1,1],[8,0,1,2,3],[1,1,1],[2,1,0,2,3,3],[2,0,2,3,2],[3,0,1,1]],[[[[4,"equipitem"],[5,"equipitem",[-5,-6,-7,-8,-9],[[7,-2],[8,-4,[[9,"d0c4d+PsndNm4cOO+dpx32j","Clickitem",-3]]]],[10,-1],[5,106,150],[-204,-95,0,0,0,0,1,1,1,1]],[1,"name",1,[[2,"凡品震天龙印",18,18,false,1,1,-10,[3],4],[11,false,2,-11,[4,4278190080]]],[0,"5ba2g1uvhMsp10JfRFQXnu",1],[5,108,22.68],[0,-50,0,0,0,0,1,1,1,1]],[6,"have",1,[[2,"×10",20,20,false,1,1,-12,[5],6],[12,2,-13,[4,4280887593]]],[0,"aaG+qhCQZMZIWrFt4ACNiZ",1],[5,42.8,29.2],[0,1,0.5],[50,-14,0,0,0,0,1,1,1,1]],[1,"frame",1,[[3,-14,[0],1]],[0,"34hI+zs7pMUaqLtKFpA6wY",1],[5,106,106],[0,22.149,0,0,0,0,1,1,1,1]],[1,"icon",1,[[13,-15,[2]]],[0,"9bEOZuveBAUbj7hPrDt9Jv",1],[5,76,74],[0,22.149,0,0,0,0,1,1,1,1]],[1,"on-head",1,[[3,-16,[7],8]],[0,"3fBDjLfS5Cq6vtAIt5Q+8k",1],[5,293,340],[-53.215,70.219,0,0,0,0,1,0.3,0.3,1]]],0,[0,3,1,0,0,1,0,4,1,0,0,1,0,-1,4,0,-2,5,0,-3,2,0,-4,3,0,-5,6,0,0,2,0,0,2,0,0,3,0,0,3,0,0,4,0,0,5,0,0,6,0,5,1,16],[0,0,0,0,0,0,0,0,0],[-1,1,-1,-1,2,-1,2,-1,1],[0,2,0,0,1,0,1,0,3]],[[{"name":"hero_avatar_1","rect":[0,0,400,400],"offset":[0,0],"originalSize":[400,400],"capInsets":[0,0,0,0]}],[4],0,[0],[6],[4]]]]