{"paths":{"0":["shikongzhan",0],"1":["lierentianchong",0],"2":["anniu",0],"3":["shenglongjian",0],"4":["home_bg",0],"5":["ejizhan",0],"6":["shengji",0],"7":["sanjuezhan",0],"8":["hit2",0],"9":["huodedaoju",0],"10":["fukongji",0],"11":["pugong1",0],"12":["pugong2",0],"13":["chuchang",0],"14":["be_attack",0],"15":["xuanwuzhan",0],"16":["battle_bg",0],"17":["siwangyinxiao",0]},"types":["cc.AudioClip"],"uuids":["23pSqN2lxJYoEoNGC7IXKg","25OIBMoRFJLISE/41kJksi","26D2DOCIxMx5mbWX0l9YLn","2d7W08hk9N25q6aqev169p","2d/ATb+ptP9pR+ZnHn/pi0","3cOqDBnaFHrpg6bkZwAGW2","43+a35OaBPPLdOzpPDnAly","5ftPanCGRCcK5N7qHh5htW","70fSclsXNIwrnqiajlo/q8","8bgjfx/4VI256KasM5J7lG","9cWRToeLFC35mr+2nAJnKf","aasPTpEmlKEL3wvoeFyAFV","b1UJzfAQlG2Joc8KECH1Ni","bdRm1RebxNO61a8wGsazR2","cdcwYIhtBM66ai0b7C0Rw5","eeQSjucv1AqZe7Wu2xrMX8","f1sMtJP9lLEa8KwJPKEMzs","f3wpqraE5PVpM9G6Co6D7y"],"scenes":{},"redirect":[],"deps":[],"packs":{},"name":"Sound","importBase":"import","nativeBase":"native","debug":false,"isZip":false,"encrypted":false,"versions":{"import":[0,"41ad2",1,"8ecd5",2,"0d34c",3,"b5659",4,"38b26",5,"5a8c8",6,"b7c13",7,"19727",8,"07e7d",9,"3832b",10,"250cd",11,"54bc4",12,"d9c4f",13,"f0141",14,"01a9a",15,"1c673",16,"0fc6c",17,"9380c"],"native":[0,"d6b0d",1,"9f8f3",2,"0e4ec",3,"b8b95",4,"74d4a",5,"4e189",6,"1550a",7,"f0dae",8,"8b38e",9,"d2ce3",10,"9995c",11,"17aad",12,"21ea2",13,"926bd",14,"93b05",15,"4266f",16,"06447",17,"fad47"]}}