[1,["ecV9IyRv1NM6Ot5B4i25XQ","cbDou6zdBBEKSWb43uTa0X","d37T76bytDNamwS3Gj64qz","b7Ec0AyxBFk4uGrCGqY7kV","babWrKyyxOfL1fcCAW7TmJ","47nxflbzNBA4wOLv0JY5FU","80uhRimeBEBbnNPcEkd5/3","941quGm+xP2LOAFtqWlxgg","9fydKoSFVGEJDfv5UOQAtf","2erdQhMIVKzZsXv9TIytUr","adsWKx5k5CBoYBXY1FRjLe","2cwyd9hhFFG5zWzKXUK37j","314CChrA9GTppBhn4ct5uf","e8ueomd5tO7KCTWgCBzJLY","fePe3t31hIkbi6pbMEciA0","a7POOCwXxI1ox59r47bEGq"],["_textureSetter","value"],["cc.SpriteFrame",["cc.AnimationClip",["_name","_duration","sample","wrapMode","curveData"],-1,11]],[[1,0,1,2,3,4,5]],[[[{"name":"Ljs_z_7","rect":[4,7,39,44],"offset":[-2,-1],"originalSize":[51,56],"capInsets":[0,0,0,0]}],[0],0,[0],[0],[0]],[[{"name":"Ljs_z_5","rect":[1,8,33,43],"offset":[-8,-1.5],"originalSize":[51,56],"capInsets":[0,0,0,0]}],[0],0,[0],[0],[1]],[[{"name":"Ljs_z_8","rect":[5,5,36,45],"offset":[-2.5,0.5],"originalSize":[51,56],"capInsets":[0,0,0,0]}],[0],0,[0],[0],[2]],[[{"name":"Ljs_z_1","rect":[6,9,31,43],"offset":[-4,-2.5],"originalSize":[51,56],"capInsets":[0,0,0,0]}],[0],0,[0],[0],[3]],[[{"name":"Ljs_z_2","rect":[6,9,29,44],"offset":[-5,-3],"originalSize":[51,56],"capInsets":[0,0,0,0]}],[0],0,[0],[0],[4]],[[[0,"z_walk",1,8,2,[{},"paths",11,[{},"Ljs_z_1",11,[{},"comps",11,[{},"cc.Sprite",11,[{},"spriteFrame",12,[[[{"frame":0},"value",6,0],[{"frame":0.125},"value",6,1],[{"frame":0.25},"value",6,2],[{"frame":0.375},"value",6,3],[{"frame":0.5},"value",6,4],[{"frame":0.625},"value",6,5],[{"frame":0.75},"value",6,6],[{"frame":0.875},"value",6,7]],11,11,11,11,11,11,11,11]]]]]]]],0,0,[0,0,0,0,0,0,0,0],[1,1,1,1,1,1,1,1],[5,6,7,8,9,10,11,12]],[[{"name":"Ljs_z_3","rect":[3,8,35,44],"offset":[-5,-2],"originalSize":[51,56],"capInsets":[0,0,0,0]}],[0],0,[0],[0],[13]],[[{"name":"Ljs_z_4","rect":[0,5,32,46],"offset":[-9.5,0],"originalSize":[51,56],"capInsets":[0,0,0,0]}],[0],0,[0],[0],[14]],[[{"name":"Ljs_z_6","rect":[2,5,35,46],"offset":[-6,0],"originalSize":[51,56],"capInsets":[0,0,0,0]}],[0],0,[0],[0],[15]]]]